PyWrike/__init__.py
PyWrike/wrike.py
PyWrike/gateways/__init__.py
PyWrike/gateways/basegateway1.py
PyWrike/gateways/oauth2gateway1.py
PyWrike-1.955.dist-info/METADATA
PyWrike-1.955.dist-info/WHEEL
PyWrike-1.955.dist-info/top_level.txt
PyWrike-1.955.dist-info/RECORD
